interpg/__init__.py
interpg/flip_data.py
interpg/interp_2d_line.py
interpg/interp_data.py
interpg/Tests/TestInterp2dLine.py
interpg/Tests/TestInterpData.py
interpg/Tests/__init__.py
interpg-1.1.0.dist-info/licenses/LICENSE.md
interpg-1.1.0.dist-info/METADATA
interpg-1.1.0.dist-info/WHEEL
interpg-1.1.0.dist-info/top_level.txt
interpg-1.1.0.dist-info/RECORD
